rfc6555.py
rfc6555-0.1.0.dist-info/LICENSE
rfc6555-0.1.0.dist-info/METADATA
rfc6555-0.1.0.dist-info/WHEEL
rfc6555-0.1.0.dist-info/top_level.txt
rfc6555-0.1.0.dist-info/RECORD
