Metadata-Version: 2.1
Name: rfc6555
Version: 0.1.0
Summary: Python implementation of the Happy Eyeballs Algorithm described in RFC 6555.
Home-page: https://www.github.com/sethmlarson/rfc6555
Author: Seth Michael Larson
Author-email: sethmichaellarson@gmail.com
Maintainer: Seth Michael Larson
Maintainer-email: sethmichaellarson@gmail.com
License: Apache-2.0
Platform: UNKNOWN
Classifier: Intended Audience :: Developers
Classifier: License :: OSI Approved :: Apache Software License
Classifier: Natural Language :: English
Classifier: Operating System :: OS Independent
Classifier: Programming Language :: Python :: 2
Classifier: Programming Language :: Python :: 2.7
Classifier: Programming Language :: Python :: 3
Classifier: Programming Language :: Python :: 3.5
Classifier: Programming Language :: Python :: 3.6
Classifier: Programming Language :: Python :: 3.7
Classifier: Programming Language :: Python :: 3.8
Classifier: Programming Language :: Python :: 3.9
Classifier: Programming Language :: Python :: 3.10
Classifier: Topic :: Internet
Classifier: Topic :: System :: Networking
License-File: LICENSE
Requires-Dist: selectors2 ; python_version < "3.4"
